{
  "filename": "vuln_002_ssrf_oauth.md",
  "mission_id": "2d122b24-bdaa-4f47-9e61-e6d5fd40c611",
  "discovered_at": "2026-03-16T12:19:06.461627",
  "target_context": {
    "target": "https://github.com/mattermost/mattermost",
    "bounty_program": "Mattermost Bug Bounty (HackerOne)",
    "repository": null,
    "mission_objectives": [
      "Find authentication bypasses",
      "Find IDOR vulnerabilities",
      "Find XSS vulnerabilities",
      "Find SSRF in integrations/webhooks",
      "Document all findings with PoC"
    ]
  },
  "archived_at": "2026-03-16T13:00:31.930209"
}